asynctoolkit/__init__.py
asynctoolkit/base.py
asynctoolkit/defaults/__init__.py
asynctoolkit/defaults/http.py
asynctoolkit/defaults/packageinstaller.py
asynctoolkit-0.2.0.dist-info/licenses/LICENCE
asynctoolkit-0.2.0.dist-info/METADATA
asynctoolkit-0.2.0.dist-info/WHEEL
asynctoolkit-0.2.0.dist-info/top_level.txt
asynctoolkit-0.2.0.dist-info/RECORD
