Metadata-Version: 2.4
Name: asynctoolkit
Version: 0.2.0
Summary: Add your description here
Requires-Python: >=3.10
License-File: LICENCE
Dynamic: license-file
